djangineer/__init__.py
djangineer/manage.py
djangineer/run.py
djangineer/config/__init__.py
djangineer/config/asgi.py
djangineer/config/settings.py
djangineer/config/urls.py
djangineer/config/wsgi.py
djangineer/ide/__init__.py
djangineer/ide/apps.py
djangineer/ide/urls.py
djangineer/ide/views.py
djangineer/ide/migrations/__init__.py
djangineer/ide/utils/error.py
djangineer-0.0.2a0.dist-info/licenses/LICENSE
djangineer-0.0.2a0.dist-info/METADATA
djangineer-0.0.2a0.dist-info/WHEEL
djangineer-0.0.2a0.dist-info/entry_points.txt
djangineer-0.0.2a0.dist-info/top_level.txt
djangineer-0.0.2a0.dist-info/RECORD
