Metadata-Version: 2.4
Name: djangineer
Version: 0.0.2a0
Summary: An experimental Django IDE
License: Apache-2.0
Requires-Python: >=3.9
License-File: LICENSE
Requires-Dist: Django>=5.0
Dynamic: license-file
